kiyoi_image_viewer/__init__.py
kiyoi_image_viewer/__main__.py
kiyoi_image_viewer/kiyoiconstants.py
kiyoi_image_viewer/kiyoimain.py
kiyoi_image_viewer/kiyoiwinreg.py
kiyoi_image_viewer/locales/cy.lang
kiyoi_image_viewer/locales/de.lang
kiyoi_image_viewer/locales/dl.lang
kiyoi_image_viewer/locales/en_gb.lang
kiyoi_image_viewer/locales/en_us.lang
kiyoi_image_viewer/locales/es.lang
kiyoi_image_viewer/locales/fr.lang
kiyoi_image_viewer/locales/hi.lang
kiyoi_image_viewer/locales/it.lang
kiyoi_image_viewer/locales/ja.lang
kiyoi_image_viewer/locales/ko.lang
kiyoi_image_viewer/locales/lang.template
kiyoi_image_viewer/locales/navi.lang
kiyoi_image_viewer/locales/ru.lang
kiyoi_image_viewer/locales/zh.lang
kiyoi_image_viewer/locales/synonyms/en.en_us.syn
kiyoi_image_viewer/locales/synonyms/en_au.en_gb.syn
kiyoi_image_viewer/locales/synonyms/en_bw.en_gb.syn
kiyoi_image_viewer/locales/synonyms/en_ca.en_gb.syn
kiyoi_image_viewer/locales/synonyms/en_er.en_gb.syn
kiyoi_image_viewer/locales/synonyms/en_et.en_gb.syn
kiyoi_image_viewer/locales/synonyms/en_fk.en_gb.syn
kiyoi_image_viewer/locales/synonyms/en_gh.en_gb.syn
kiyoi_image_viewer/locales/synonyms/en_gi.en_gb.syn
kiyoi_image_viewer/locales/synonyms/en_gm.en_gb.syn
kiyoi_image_viewer/locales/synonyms/en_gy.en_gb.syn
kiyoi_image_viewer/locales/synonyms/en_hk.en_gb.syn
kiyoi_image_viewer/locales/synonyms/en_ie.en_gb.syn
kiyoi_image_viewer/locales/synonyms/en_in.en_gb.syn
kiyoi_image_viewer/locales/synonyms/en_io.en_gb.syn
kiyoi_image_viewer/locales/synonyms/en_je.en_gb.syn
kiyoi_image_viewer/locales/synonyms/en_jp.en_us.syn
kiyoi_image_viewer/locales/synonyms/en_ke.en_gb.syn
kiyoi_image_viewer/locales/synonyms/en_lr.en_gb.syn
kiyoi_image_viewer/locales/synonyms/en_ls.en_gb.syn
kiyoi_image_viewer/locales/synonyms/en_mg.en_gb.syn
kiyoi_image_viewer/locales/synonyms/en_mt.en_gb.syn
kiyoi_image_viewer/locales/synonyms/en_mw.en_gb.syn
kiyoi_image_viewer/locales/synonyms/en_na.en_gb.syn
kiyoi_image_viewer-0.1.2.dist-info/LICENSE.txt
kiyoi_image_viewer-0.1.2.dist-info/METADATA
kiyoi_image_viewer-0.1.2.dist-info/WHEEL
kiyoi_image_viewer-0.1.2.dist-info/entry_points.txt
kiyoi_image_viewer-0.1.2.dist-info/top_level.txt
kiyoi_image_viewer-0.1.2.dist-info/RECORD
