Metadata-Version: 2.1
Name: kiyoi_image_viewer
Version: 0.1.2
Summary: Kiyoi Image Viewer
Author-email: William Kappler <WilliamKappler@gmail.com>
License: LICENSE.txt
Project-URL: Github, https://github.com/WilliamKappler/kiyoi/
Project-URL: Sourceforge, https://sourceforge.net/projects/kiyoi-image-viewer/
Keywords: Image Viewer,Qt
Classifier: Development Status :: 3 - Alpha
Classifier: License :: OSI Approved :: ISC License (ISCL)
Classifier: Programming Language :: Python :: 3 :: Only
Classifier: Topic :: Artistic Software
Classifier: Topic :: Multimedia :: Graphics
Classifier: Topic :: Multimedia :: Graphics :: Viewers
Classifier: Topic :: Utilities
Classifier: Environment :: X11 Applications
Classifier: Environment :: X11 Applications :: Qt
Classifier: Intended Audience :: End Users/Desktop
Classifier: Natural Language :: English
Classifier: Operating System :: Microsoft :: Windows
Classifier: Operating System :: Microsoft :: Windows :: Windows 7
Classifier: Operating System :: Microsoft :: Windows :: Windows 8
Classifier: Operating System :: Microsoft :: Windows :: Windows 8.1
Classifier: Operating System :: Microsoft :: Windows :: Windows 10
Classifier: Operating System :: Microsoft :: Windows :: Windows 11
Classifier: Operating System :: POSIX :: BSD
Classifier: Operating System :: POSIX :: Linux
License-File: LICENSE.txt
Requires-Dist: PySide6
Requires-Dist: pyperclip
Requires-Dist: pillow
